dask_janelia/__init__.py
dask_janelia/context.py
dask_janelia/deploy.py
dask_janelia/utils.py
dask_janelia-0.1.5.dist-info/LICENSE.txt
dask_janelia-0.1.5.dist-info/WHEEL
dask_janelia-0.1.5.dist-info/METADATA
dask_janelia-0.1.5.dist-info/RECORD
