Metadata-Version: 2.1
Name: dask-janelia
Version: 0.1.5
Summary: Simple dask distributed deployment for the Janelia Research Campus compute cluster.
License: MIT
Author: Davis Vann Bennett
Author-email: davis.v.bennett@gmail.com
Requires-Python: >=3.8,<4.0
Classifier: License :: OSI Approved :: MIT License
Classifier: Programming Language :: Python :: 3
Classifier: Programming Language :: Python :: 3.8
Classifier: Programming Language :: Python :: 3.9
Requires-Dist: dask-jobqueue (>=0.7.1,<0.8.0)
Requires-Dist: distributed (>=2022.6.0,<2023.0.0)
